chatutils/__init__.py
chatutils/display.py
chatutils/io.py
chatutils/parsing.py
chatutils/role.py
chatutils/text.py
chatutils-0.1.0.dist-info/licenses/LICENSE
chatutils-0.1.0.dist-info/METADATA
chatutils-0.1.0.dist-info/WHEEL
chatutils-0.1.0.dist-info/top_level.txt
chatutils-0.1.0.dist-info/RECORD
