Metadata-Version: 2.4
Name: chatutils
Version: 0.1.0
Summary: Utility methods to manipulate LLM inputs and outputs
Author: Kyo Takano
License: MIT License
Project-URL: Source, https://github.com/kyo-takano/chatutils
Keywords: LLM,code,agent,io
Classifier: Development Status :: 3 - Alpha
Classifier: Operating System :: OS Independent
Classifier: Intended Audience :: Developers
Classifier: License :: OSI Approved :: MIT License
Classifier: Programming Language :: Python :: 3.8
Classifier: Programming Language :: Python :: 3.9
Classifier: Programming Language :: Python :: 3.10
Classifier: Programming Language :: Python :: 3.11
Classifier: Programming Language :: Python :: 3.12
Classifier: Programming Language :: Python :: 3 :: Only
Requires-Python: >=3.8
License-File: LICENSE
Requires-Dist: rich
Dynamic: license-file
